rainiee_engine/__init__.py
rainiee_engine/data_pro.py
rainiee_engine/base/__init__.py
rainiee_engine/base/client.py
rainiee_engine/base/login.py
rainiee_engine/base/upass.py
rainiee_engine-3.0.0.dist-info/METADATA
rainiee_engine-3.0.0.dist-info/WHEEL
rainiee_engine-3.0.0.dist-info/top_level.txt
rainiee_engine-3.0.0.dist-info/RECORD
