Metadata-Version: 2.1
Name: rainiee-engine
Version: 3.0.0
Summary: rainiee decision engine api
Home-page: https://github.com/Rainiee-Technology/rainiee_algorithm
Author: rainiee
Author-email: rainiee@163.com
License: MIT
Platform: UNKNOWN
Requires-Python: >=3
